eniris/__init__.py
eniris/driver.py
eniris/py.typed
eniris/point/__init__.py
eniris/point/namespace.py
eniris/point/point.py
eniris/point/writer/__init__.py
eniris/point/writer/buffered.py
eniris/point/writer/direct.py
eniris/point/writer/filter.py
eniris/point/writer/stats.py
eniris/point/writer/writer.py
eniris/telemessage/__init__.py
eniris/telemessage/telemessage.py
eniris/telemessage/writer/__init__.py
eniris/telemessage/writer/background.py
eniris/telemessage/writer/direct.py
eniris/telemessage/writer/gzipped.py
eniris/telemessage/writer/pooled.py
eniris/telemessage/writer/writer.py
eniris-0.9.3.dist-info/licenses/LICENSE
eniris-0.9.3.dist-info/METADATA
eniris-0.9.3.dist-info/WHEEL
eniris-0.9.3.dist-info/top_level.txt
eniris-0.9.3.dist-info/RECORD
