Metadata-Version: 2.4
Name: eniris
Version: 0.9.3
Summary: Eniris API driver for Python
Home-page: https://github.com/eniris-international/eniris-api-python-driver
Download-URL: https://github.com/eniris-international/eniris-api-python-driver/archive/refs/tags/v0.9.3.tar.gz
Author: Enris BV
Author-email: info@eniris.be
License: MIT
Keywords: eniris,api,rest
Classifier: Development Status :: 4 - Beta
Classifier: Intended Audience :: Developers
Classifier: Topic :: Software Development :: Build Tools
Classifier: License :: OSI Approved :: MIT License
Classifier: Programming Language :: Python :: 3
License-File: LICENSE
Requires-Dist: requests
Dynamic: author
Dynamic: author-email
Dynamic: classifier
Dynamic: description
Dynamic: description-content-type
Dynamic: download-url
Dynamic: home-page
Dynamic: keywords
Dynamic: license
Dynamic: license-file
Dynamic: requires-dist
Dynamic: summary
